piexin/__init__.py
piexin/entrypoint.py
piexin/inventorywriter/__init__.py
piexin/inventorywriter/inventorywriter.py
piexin/phpipam/__init__.py
piexin/phpipam/address.py
piexin/phpipam/exeption.py
piexin/phpipam/phpipam.py
piexin/phpipam/section.py
piexin/phpipam/subnet.py
piexin/phpipam/vlan.py
tests/__init__.py
tests/test_address.py
tests/test_basic.py
tests/test_hostnames.py
tests/test_inventorywriter.py
piexin-1.0.2.dist-info/LICENSE
piexin-1.0.2.dist-info/METADATA
piexin-1.0.2.dist-info/WHEEL
piexin-1.0.2.dist-info/entry_points.txt
piexin-1.0.2.dist-info/top_level.txt
piexin-1.0.2.dist-info/RECORD
