Metadata-Version: 2.1
Name: piexin
Version: 1.0.2
Summary: phpipam export to ansible inventory ini file
Home-page: http://github.com/aufbaubank/piexin
Author: Daniel Henneberg
Author-email: daniel.henneberg@aufbaubank.de
License: MIT
Platform: UNKNOWN
Requires-Python: >=3.6
Requires-Dist: requests
